sheetsmart/__init__.py
sheetsmart/bar.py
sheetsmart/bar5.py
sheetsmart/biplot.py
sheetsmart/feedback.py
sheetsmart/in_pkg.py
sheetsmart/mkcopy.py
sheetsmart/modify.py
sheetsmart/read.py
sheetsmart/write.py
sheetsmart-2.1.dist-info/METADATA
sheetsmart-2.1.dist-info/WHEEL
sheetsmart-2.1.dist-info/top_level.txt
sheetsmart-2.1.dist-info/RECORD
