Metadata-Version: 2.4
Name: sheetsmart
Version: 2.1
Summary: SheetSmart: Intelligent spreadsheet management tool for enhanced data handling and automation.
Home-page: https://github.com/bhuvanesh-m-dev/sheetsmart
Author: Bhuvanesh M
Author-email: bhuvaneshm.developer@gmail.com
License: GPLv3 or Sheetsmart Commercial License
Project-URL: Portfolio, https://bhuvaneshm.in
Project-URL: LinkedIn, https://www.linkedin.com/in/bhuvaneshm-developer
Project-URL: GitHub Repository, https://github.com/bhuvanesh-m-dev
Classifier: Programming Language :: Python :: 3
Classifier: License :: OSI Approved :: GNU General Public License v3 (GPLv3)
Classifier: Operating System :: OS Independent
Requires-Python: >=3.6
Dynamic: author
Dynamic: author-email
Dynamic: classifier
Dynamic: description
Dynamic: description-content-type
Dynamic: home-page
Dynamic: license
Dynamic: project-url
Dynamic: requires-python
Dynamic: summary
